kb4api/__init__.py
kb4api-0.1.1.dist-info/LICENSE.md
kb4api-0.1.1.dist-info/METADATA
kb4api-0.1.1.dist-info/WHEEL
kb4api-0.1.1.dist-info/top_level.txt
kb4api-0.1.1.dist-info/RECORD
